tap_clickup/__init__.py
tap_clickup/client.py
tap_clickup/schemas/custom_field.json
tap_clickup/schemas/folder.json
tap_clickup/schemas/goal.json
tap_clickup/schemas/list.json
tap_clickup/schemas/shared.json
tap_clickup/schemas/space.json
tap_clickup/schemas/tag.json
tap_clickup/schemas/task.json
tap_clickup/schemas/task_template.json
tap_clickup/schemas/team.json
tap_clickup/schemas/time_entries.json
tap_clickup/streams.py
tap_clickup/tap.py
tap_clickup/tests/__init__.py
tap_clickup/tests/archived_task.json
tap_clickup/tests/archived_task_two.json
tap_clickup/tests/task.json
tap_clickup/tests/task_two.json
tap_clickup/tests/test_core.py
tap_clickup/tests/test_state.py
tap_clickup/tests/test_streams.py
tap_clickup-0.0.23.dist-info/LICENSE
tap_clickup-0.0.23.dist-info/METADATA
tap_clickup-0.0.23.dist-info/WHEEL
tap_clickup-0.0.23.dist-info/entry_points.txt
tap_clickup-0.0.23.dist-info/RECORD
