Metadata-Version: 2.1
Name: tap-clickup
Version: 0.0.23
Summary: tap-clickup is a Singer tap for ClickUp by AutoIDM
Home-page: https://autoidm.com
Keywords: AutoIDM,Auto IDM,tap-clickup,clickup,tap,singer,sdk
Author: AutoIDM
Maintainer: AutoIDM
Requires-Python: >=3.7.1,<3.12
Classifier: Programming Language :: Python :: 3
Classifier: Programming Language :: Python :: 3.8
Classifier: Programming Language :: Python :: 3.9
Classifier: Programming Language :: Python :: 3.10
Classifier: Programming Language :: Python :: 3.11
Requires-Dist: requests (>=2.25.1,<3.0.0)
Requires-Dist: singer-sdk (==0.29.0)
Project-URL: Documentation, https://github.com/AutoIDM/tap-clickup
Project-URL: Issues, https://github.com/AutoIDM/tap-clickup/issues
Project-URL: LinkedIn, https://www.linkedin.com/company/68741135
Project-URL: Repository, https://github.com/AutoIDM/tap-clickup
Project-URL: Twitter, https://twitter.com/AutoIDM
Project-URL: Youtube, https://www.youtube.com/channel/UCk4lfv8fZ4rMlYzw9N_FM0g
